embestore/__init__.py
embestore/cli/__init__.py
embestore/cli/main.py
embestore/cli/serve.py
embestore/store/__init__.py
embestore/store/base.py
embestore/store/jina.py
embestore/store/torch.py
embestore/utils.py
embestore/version.py
embestore-1.0.1.dist-info/WHEEL
embestore-1.0.1.dist-info/METADATA
embestore-1.0.1.dist-info/entry_points.txt
embestore-1.0.1.dist-info/LICENSE
embestore-1.0.1.dist-info/RECORD
