Metadata-Version: 2.1
Name: embestore
Version: 1.0.1
Summary: 
Author: Yoshi Gao
Author-email: yoshi4868686@gmail.com
Requires-Python: >=3.9,<4.0
Classifier: Programming Language :: Python :: 3
Classifier: Programming Language :: Python :: 3.9
Classifier: Programming Language :: Python :: 3.10
Classifier: Programming Language :: Python :: 3.11
Provides-Extra: jina
Provides-Extra: sentence-transformers
Requires-Dist: jina (>=3.13.2,<4.0.0) ; extra == "jina"
Requires-Dist: numpy (>=1.24.1,<2.0.0)
Requires-Dist: pandas (>=1.5.2,<2.0.0)
Requires-Dist: pyarrow (>=11.0.0,<12.0.0)
Requires-Dist: sentence-transformers (>=2.2.2,<3.0.0) ; extra == "sentence-transformers"
Requires-Dist: torch (>=1.13.1,<2.0.0) ; extra == "sentence-transformers"
Requires-Dist: typer[all] (>=0.7.0,<0.8.0)
